pytest_django_ordering/__init__.py
pytest_django_ordering/plugin.py
pytest_django_ordering-1.2.0.dist-info/LICENSE
pytest_django_ordering-1.2.0.dist-info/METADATA
pytest_django_ordering-1.2.0.dist-info/WHEEL
pytest_django_ordering-1.2.0.dist-info/entry_points.txt
pytest_django_ordering-1.2.0.dist-info/top_level.txt
pytest_django_ordering-1.2.0.dist-info/RECORD
