Metadata-Version: 2.1
Name: pytest-django-ordering
Version: 1.2.0
Summary: A pytest plugin for preserving the order in which Django runs tests.
Home-page: https://github.com/rlucioni/pytest-django-ordering
Author: Renzo Lucioni
Author-email: renzo@lucioni.xyz
License: MIT
Platform: UNKNOWN
Classifier: Programming Language :: Python
Classifier: Development Status :: 5 - Production/Stable
Classifier: License :: OSI Approved :: MIT License
Classifier: Topic :: Software Development :: Libraries :: Python Modules
Classifier: Framework :: Django
Classifier: Framework :: Pytest
Requires-Dist: django
Requires-Dist: pytest (>=2.3.0)
Requires-Dist: pytest-django
